bhoonidhi/__init__.py
bhoonidhi/bhoonidhiSmartOrdering.py
bhoonidhi/bhoonidhi_helper.py
bhoonidhi/utils.py
bhoonidhi/SmartSearch/__init__.py
bhoonidhi/SmartSearch/bhoonidhiSmartOrdering.py
bhoonidhi/SmartSearch/bhoonidhi_helper.py
bhoonidhi/SmartSearch/nltk_modules.py
bhoonidhi/SmartSearch/utils.py
bhoonidhi-0.1.0.dist-info/METADATA
bhoonidhi-0.1.0.dist-info/WHEEL
bhoonidhi-0.1.0.dist-info/top_level.txt
bhoonidhi-0.1.0.dist-info/RECORD
