Metadata-Version: 2.1
Name: bhoonidhi
Version: 0.1.0
Summary: Useful tools to work with Bhoonidhi (ISRO's open data access portal) in Python
Home-page: https://github.com/RohitGandikota/bhoonidhi
Author: Rohit Gandikota
Author-email: grohit3107@gmail.com
License: MIT
Download-URL: https://pypi.org/project/bhoonidhi/
Keywords: bhoonidhi,SmartSearch,NLP,AI
Platform: UNKNOWN
Requires-Dist: nltk
Requires-Dist: dateparser
Requires-Dist: quantulum3
Requires-Dist: word2number
Requires-Dist: numpy
Requires-Dist: requests
Requires-Dist: datetime
Requires-Dist: stemming
